patent_mcp_server/__init__.py
patent_mcp_server/__main__.py
patent_mcp_server/config.py
patent_mcp_server/constants.py
patent_mcp_server/patents.py
patent_mcp_server/prompts.py
patent_mcp_server/resources.py
patent_mcp_server/json/search_query.json
patent_mcp_server/patentsview/__init__.py
patent_mcp_server/patentsview/patentsview_client.py
patent_mcp_server/uspto/__init__.py
patent_mcp_server/uspto/api_uspto_gov.py
patent_mcp_server/uspto/enriched_citation_client.py
patent_mcp_server/uspto/litigation_client.py
patent_mcp_server/uspto/office_action_client.py
patent_mcp_server/uspto/ppubs_uspto_gov.py
patent_mcp_server/uspto/ptab_client.py
patent_mcp_server/util/__init__.py
patent_mcp_server/util/errors.py
patent_mcp_server/util/logging.py
patent_mcp_server/util/response.py
patent_mcp_server/util/validation.py
patent_mcp_server-0.6.0.dist-info/licenses/LICENSE.md
patent_mcp_server-0.6.0.dist-info/METADATA
patent_mcp_server-0.6.0.dist-info/WHEEL
patent_mcp_server-0.6.0.dist-info/entry_points.txt
patent_mcp_server-0.6.0.dist-info/top_level.txt
patent_mcp_server-0.6.0.dist-info/RECORD
