Metadata-Version: 2.4
Name: patent-mcp-server
Version: 0.6.0
Summary: Model Context Protocol server for USPTO patent data
Author-email: riemannzeta <noreply@github.com>
License-Expression: MIT
Project-URL: Homepage, https://github.com/riemannzeta/patent_mcp_server
Project-URL: Repository, https://github.com/riemannzeta/patent_mcp_server
Project-URL: Issues, https://github.com/riemannzeta/patent_mcp_server/issues
Keywords: mcp,model-context-protocol,uspto,patent,patent-search,api
Classifier: Development Status :: 4 - Beta
Classifier: Intended Audience :: Developers
Classifier: Intended Audience :: Legal Industry
Classifier: Programming Language :: Python :: 3
Classifier: Programming Language :: Python :: 3.10
Classifier: Programming Language :: Python :: 3.11
Classifier: Programming Language :: Python :: 3.12
Classifier: Programming Language :: Python :: 3.13
Classifier: Topic :: Software Development :: Libraries :: Python Modules
Classifier: Topic :: Scientific/Engineering :: Information Analysis
Requires-Python: <3.14,>=3.10
License-File: LICENSE.md
Requires-Dist: h2>=4.2.0
Requires-Dist: httpx>=0.28.1
Requires-Dist: mcp[cli]>=1.3.0
Requires-Dist: python-dotenv>=1.0.1
Requires-Dist: pydantic>=2.0.0
Requires-Dist: tenacity>=8.0.0
Provides-Extra: dev
Requires-Dist: pytest>=7.0.0; extra == "dev"
Requires-Dist: pytest-asyncio<0.25.0,>=0.21.0; extra == "dev"
Requires-Dist: pytest-cov>=4.0.0; extra == "dev"
Dynamic: license-file
